{
  "url" : "http://hl7.org/fhir/uv/phr/ImplementationGuide/hl7.fhir.uv.phr",
  "name" : "PatientHealthRecordsIG",
  "title" : "Personal Health Records",
  "description" : "Guidance on how to create longitudinal personal health records using FHIR.  Exporting, file formats, patient examples, and more.",
  "status" : "draft",
  "package-id" : "hl7.fhir.uv.phr",
  "ig-ver" : "1.0.0-ballot",
  "date" : "Thu, 20 Mar, 2025 16:03:56 -0500",
  "dateISO8601" : "2025-03-20T16:03:56-05:00",
  "errs" : 1,
  "warnings" : 2,
  "hints" : 1,
  "suppressed-hints" : 4,
  "suppressed-warnings" : 0,
  "version" : "4.0.1",
  "tool" : "5.0.0 (3)",
  "maxMemory" : 2701758440
}
